{
  "source": "assets/vsic-vn/vsic-2025.xlsx",
  "total_vsic_count": 5,
  "vsic_list": [
    {
      "code": "5621",
      "title": "Cung cấp dịch vụ ăn uống theo hợp đồng không thường xuyên với khách hàng",
      "children_level5": [
        {
          "code": "56210",
          "title": "Cung cấp dịch vụ ăn uống theo hợp đồng không thường xuyên với khách hàng"
        }
      ]
    },
    {
      "code": "5629",
      "title": "Dịch vụ ăn uống khác",
      "children_level5": [
        {
          "code": "56290",
          "title": "Dịch vụ ăn uống khác"
        }
      ]
    },
    {
      "code": "5630",
      "title": "Dịch vụ phục vụ đồ uống",
      "children_level5": [
        {
          "code": "56301",
          "title": "Quán rượu, bia, quầy bar"
        },
        {
          "code": "56302",
          "title": "Quán cà phê, giải khát"
        },
        {
          "code": "56309",
          "title": "Dịch vụ phục vụ đồ uống khác"
        }
      ]
    },
    {
      "code": "5640",
      "title": "Hoạt động dịch vụ trung gian cho dịch vụ ăn uống",
      "children_level5": [
        {
          "code": "56400",
          "title": "Hoạt động dịch vụ trung gian cho dịch vụ ăn uống"
        }
      ]
    },
    {
      "code": "5811",
      "title": "Xuất bản sách",
      "children_level5": [
        {
          "code": "58110",
          "title": "Xuất bản sách"
        }
      ]
    }
  ]
}